smithy_http/__init__.py
smithy_http/bindings.py
smithy_http/deserializers.py
smithy_http/endpoints.py
smithy_http/exceptions.py
smithy_http/py.typed
smithy_http/restjson.py
smithy_http/serializers.py
smithy_http/user_agent.py
smithy_http/utils.py
smithy_http/aio/__init__.py
smithy_http/aio/aiohttp.py
smithy_http/aio/crt.py
smithy_http/aio/protocols.py
smithy_http/aio/restjson.py
smithy_http/aio/auth/__init__.py
smithy_http/aio/auth/apikey.py
smithy_http/aio/identity/__init__.py
smithy_http/aio/identity/apikey.py
smithy_http/aio/interfaces/__init__.py
smithy_http/interceptors/__init__.py
smithy_http/interceptors/user_agent.py
smithy_http/interfaces/__init__.py
smithy_http/plugins/__init__.py
smithy_http-0.1.0.dist-info/METADATA
smithy_http-0.1.0.dist-info/WHEEL
smithy_http-0.1.0.dist-info/licenses/NOTICE
smithy_http-0.1.0.dist-info/RECORD
