Metadata-Version: 2.4
Name: smithy-http
Version: 0.1.0
Summary: HTTP components for Smithy tooling.
Project-URL: Changelog, https://github.com/smithy-lang/smithy-python/blob/develop/packages/smithy-http/CHANGELOG.md
Project-URL: Code, https://github.com/smithy-lang/smithy-python/blob/develop/packages/smithy-http/
Project-URL: Issue tracker, https://github.com/smithy-lang/smithy-python/issues
Author: Amazon Web Services
License: Apache License 2.0
License-File: NOTICE
Keywords: http,sdk,smithy
Classifier: Development Status :: 2 - Pre-Alpha
Classifier: Intended Audience :: Developers
Classifier: Intended Audience :: System Administrators
Classifier: License :: OSI Approved :: Apache Software License
Classifier: Natural Language :: English
Classifier: Operating System :: OS Independent
Classifier: Programming Language :: Python
Classifier: Programming Language :: Python :: 3
Classifier: Programming Language :: Python :: 3 :: Only
Classifier: Programming Language :: Python :: 3.12
Classifier: Programming Language :: Python :: 3.13
Classifier: Programming Language :: Python :: 3.14
Classifier: Programming Language :: Python :: Implementation :: CPython
Classifier: Topic :: Software Development :: Libraries
Requires-Python: >=3.12
Requires-Dist: smithy-core~=0.1.0
Provides-Extra: aiohttp
Requires-Dist: aiohttp<4.0,>=3.11.12; extra == 'aiohttp'
Requires-Dist: yarl; extra == 'aiohttp'
Provides-Extra: awscrt
Requires-Dist: awscrt>=0.23.10; extra == 'awscrt'
